{
  "apply_gate": "Do not run apply SQL without explicit approval for the exact command.",
  "backup_table": "manaloom_deploy_audit.pg866_board_wipe_neutral_auxiliary_20260713_054814",
  "deploy_id": "pg866",
  "execution_scenarios": [
    {
      "card": {
        "name": "Akroma's Vengeance",
        "type_line": "Sorcery"
      },
      "destroy_card_types": [
        "artifact",
        "creature",
        "enchantment"
      ],
      "destroy_controller": "any",
      "logical_rule_key": "battle_rule_v1:a003e239c83a3dbda454e5f284772921",
      "name": "Akroma's Vengeance destroys matching permanents",
      "type": "board_wipe"
    },
    {
      "card": {
        "name": "Fuel the Flames",
        "type_line": "Instant"
      },
      "expected_damage": 2,
      "expected_damage_players": false,
      "expected_damage_scope": "each_creature",
      "logical_rule_key": "battle_rule_v1:fd2d6f103034bb760e37bcdba5ca7183",
      "name": "Fuel the Flames deals damage to matching permanents",
      "type": "damage_wipe"
    },
    {
      "card": {
        "name": "Hush",
        "type_line": "Sorcery"
      },
      "destroy_card_types": [
        "enchantment"
      ],
      "destroy_controller": "any",
      "logical_rule_key": "battle_rule_v1:8cca937904da37d443131e25b0e866a5",
      "name": "Hush destroys matching permanents",
      "type": "board_wipe"
    },
    {
      "_cast_context": {
        "x_value": 3
      },
      "card": {
        "name": "Starstorm",
        "type_line": "Instant"
      },
      "expected_damage": 3,
      "expected_damage_players": false,
      "expected_damage_scope": "each_creature",
      "expected_x_value": 3,
      "logical_rule_key": "battle_rule_v1:529435595dfa892ca9d7d99e56608b91",
      "name": "Starstorm deals damage to matching permanents",
      "type": "damage_wipe",
      "x_value": 3
    },
    {
      "card": {
        "name": "Sweltering Suns",
        "type_line": "Sorcery"
      },
      "expected_damage": 3,
      "expected_damage_players": false,
      "expected_damage_scope": "each_creature",
      "logical_rule_key": "battle_rule_v1:d3f4bf0986864fe567d07cacb4c295a5",
      "name": "Sweltering Suns deals damage to matching permanents",
      "type": "damage_wipe"
    }
  ],
  "expected_rules": [
    {
      "card_name": "Akroma's Vengeance",
      "execution_status": "auto",
      "forbid_annotation_only": true,
      "logical_rule_key": "battle_rule_v1:a003e239c83a3dbda454e5f284772921",
      "min_rule_version": 2,
      "normalized_name": "akroma's vengeance",
      "oracle_hash": "aadc4c2605e84b2eb59448c85fd9e2b6",
      "required_effect_fields": {
        "battle_model_scope": "xmage_destroy_all_matching_permanents_spell_v1",
        "destination": "graveyard",
        "destroy_card_types": [
          "artifact",
          "creature",
          "enchantment"
        ],
        "effect": "board_wipe",
        "instant": false,
        "sorcery": true,
        "xmage_effect_class": "DestroyAllEffect"
      },
      "review_status": "verified"
    },
    {
      "card_name": "Fuel the Flames",
      "execution_status": "auto",
      "forbid_annotation_only": true,
      "logical_rule_key": "battle_rule_v1:fd2d6f103034bb760e37bcdba5ca7183",
      "min_rule_version": 2,
      "normalized_name": "fuel the flames",
      "oracle_hash": "cc94266044f2110700f72f897057280c",
      "required_effect_fields": {
        "amount": 2,
        "battle_model_scope": "xmage_fixed_damage_all_matching_permanents_spell_v1",
        "damage": 2,
        "damage_scope": "each_creature",
        "effect": "damage_wipe",
        "instant": true,
        "sorcery": false,
        "xmage_effect_class": "DamageAllEffect"
      },
      "review_status": "verified"
    },
    {
      "card_name": "Hush",
      "execution_status": "auto",
      "forbid_annotation_only": true,
      "logical_rule_key": "battle_rule_v1:8cca937904da37d443131e25b0e866a5",
      "min_rule_version": 2,
      "normalized_name": "hush",
      "oracle_hash": "5c6bffbefc286bfe2ac0b15e7616894d",
      "required_effect_fields": {
        "battle_model_scope": "xmage_destroy_all_matching_permanents_spell_v1",
        "destination": "graveyard",
        "destroy_card_types": [
          "enchantment"
        ],
        "effect": "board_wipe",
        "instant": false,
        "sorcery": true,
        "xmage_effect_class": "DestroyAllEffect"
      },
      "review_status": "verified"
    },
    {
      "card_name": "Starstorm",
      "execution_status": "auto",
      "forbid_annotation_only": true,
      "logical_rule_key": "battle_rule_v1:529435595dfa892ca9d7d99e56608b91",
      "min_rule_version": 2,
      "normalized_name": "starstorm",
      "oracle_hash": "a9aa5a9ca98fa85f0d75ec12d20fc4b4",
      "required_effect_fields": {
        "amount": 0,
        "battle_model_scope": "xmage_fixed_damage_all_matching_permanents_spell_v1",
        "damage": 0,
        "damage_amount_source": "x_value",
        "damage_scope": "each_creature",
        "effect": "damage_wipe",
        "instant": true,
        "sorcery": false,
        "xmage_effect_class": "DamageAllEffect"
      },
      "review_status": "verified"
    },
    {
      "card_name": "Sweltering Suns",
      "execution_status": "auto",
      "forbid_annotation_only": true,
      "logical_rule_key": "battle_rule_v1:d3f4bf0986864fe567d07cacb4c295a5",
      "min_rule_version": 2,
      "normalized_name": "sweltering suns",
      "oracle_hash": "060c6a7021fce3a0cafe3a08adfb38cb",
      "required_effect_fields": {
        "amount": 3,
        "battle_model_scope": "xmage_fixed_damage_all_matching_permanents_spell_v1",
        "damage": 3,
        "damage_scope": "each_creature",
        "effect": "damage_wipe",
        "instant": false,
        "sorcery": true,
        "xmage_effect_class": "DamageAllEffect"
      },
      "review_status": "verified"
    }
  ],
  "family_counts": {
    "xmage_damage_all_spell": 2,
    "xmage_destroy_all_spell": 2,
    "xmage_x_damage_all_spell": 1
  },
  "files": {
    "apply": "docs/hermes-analysis/master_optimizer_reports/pg866_board_wipe_neutral_auxiliary_new_server_apply.sql",
    "manifest": "docs/hermes-analysis/master_optimizer_reports/pg866_board_wipe_neutral_auxiliary_new_server_manifest.json",
    "package": "docs/hermes-analysis/master_optimizer_reports/pg866_board_wipe_neutral_auxiliary_new_server_package.md",
    "postcheck": "docs/hermes-analysis/master_optimizer_reports/pg866_board_wipe_neutral_auxiliary_new_server_postcheck.sql",
    "precheck": "docs/hermes-analysis/master_optimizer_reports/pg866_board_wipe_neutral_auxiliary_new_server_precheck.sql",
    "rollback": "docs/hermes-analysis/master_optimizer_reports/pg866_board_wipe_neutral_auxiliary_new_server_rollback.sql"
  },
  "generated_at": "2026-07-13T05:50:31+00:00",
  "mutations_performed": [],
  "runtime_checks": [
    {
      "card": {
        "name": "Akroma's Vengeance"
      },
      "card_name": "Akroma's Vengeance",
      "effect": "board_wipe",
      "forbid_annotation_only": true,
      "logical_rule_key": "battle_rule_v1:a003e239c83a3dbda454e5f284772921",
      "normalized_name": "akroma's vengeance",
      "required_effect_fields": {
        "battle_model_scope": "xmage_destroy_all_matching_permanents_spell_v1",
        "destination": "graveyard",
        "destroy_card_types": [
          "artifact",
          "creature",
          "enchantment"
        ],
        "effect": "board_wipe",
        "instant": false,
        "sorcery": true,
        "xmage_effect_class": "DestroyAllEffect"
      }
    },
    {
      "card": {
        "name": "Fuel the Flames"
      },
      "card_name": "Fuel the Flames",
      "effect": "damage_wipe",
      "forbid_annotation_only": true,
      "logical_rule_key": "battle_rule_v1:fd2d6f103034bb760e37bcdba5ca7183",
      "normalized_name": "fuel the flames",
      "required_effect_fields": {
        "amount": 2,
        "battle_model_scope": "xmage_fixed_damage_all_matching_permanents_spell_v1",
        "damage": 2,
        "damage_scope": "each_creature",
        "effect": "damage_wipe",
        "instant": true,
        "sorcery": false,
        "xmage_effect_class": "DamageAllEffect"
      }
    },
    {
      "card": {
        "name": "Hush"
      },
      "card_name": "Hush",
      "effect": "board_wipe",
      "forbid_annotation_only": true,
      "logical_rule_key": "battle_rule_v1:8cca937904da37d443131e25b0e866a5",
      "normalized_name": "hush",
      "required_effect_fields": {
        "battle_model_scope": "xmage_destroy_all_matching_permanents_spell_v1",
        "destination": "graveyard",
        "destroy_card_types": [
          "enchantment"
        ],
        "effect": "board_wipe",
        "instant": false,
        "sorcery": true,
        "xmage_effect_class": "DestroyAllEffect"
      }
    },
    {
      "card": {
        "name": "Starstorm"
      },
      "card_name": "Starstorm",
      "effect": "damage_wipe",
      "forbid_annotation_only": true,
      "logical_rule_key": "battle_rule_v1:529435595dfa892ca9d7d99e56608b91",
      "normalized_name": "starstorm",
      "required_effect_fields": {
        "amount": 0,
        "battle_model_scope": "xmage_fixed_damage_all_matching_permanents_spell_v1",
        "damage": 0,
        "damage_amount_source": "x_value",
        "damage_scope": "each_creature",
        "effect": "damage_wipe",
        "instant": true,
        "sorcery": false,
        "xmage_effect_class": "DamageAllEffect"
      }
    },
    {
      "card": {
        "name": "Sweltering Suns"
      },
      "card_name": "Sweltering Suns",
      "effect": "damage_wipe",
      "forbid_annotation_only": true,
      "logical_rule_key": "battle_rule_v1:d3f4bf0986864fe567d07cacb4c295a5",
      "normalized_name": "sweltering suns",
      "required_effect_fields": {
        "amount": 3,
        "battle_model_scope": "xmage_fixed_damage_all_matching_permanents_spell_v1",
        "damage": 3,
        "damage_scope": "each_creature",
        "effect": "damage_wipe",
        "instant": false,
        "sorcery": true,
        "xmage_effect_class": "DamageAllEffect"
      }
    }
  ],
  "selected_card_names": [
    "Akroma's Vengeance",
    "Fuel the Flames",
    "Hush",
    "Starstorm",
    "Sweltering Suns"
  ],
  "selected_count": 5,
  "slug": "board_wipe_neutral_auxiliary",
  "snapshot_checks": [
    {
      "card_name": "Akroma's Vengeance",
      "execution_status": "auto",
      "forbid_annotation_only": true,
      "logical_rule_key": "battle_rule_v1:a003e239c83a3dbda454e5f284772921",
      "min_rule_version": 2,
      "normalized_name": "akroma's vengeance",
      "oracle_hash": "aadc4c2605e84b2eb59448c85fd9e2b6",
      "required_effect_fields": {
        "battle_model_scope": "xmage_destroy_all_matching_permanents_spell_v1"
      },
      "review_status": "verified"
    },
    {
      "card_name": "Fuel the Flames",
      "execution_status": "auto",
      "forbid_annotation_only": true,
      "logical_rule_key": "battle_rule_v1:fd2d6f103034bb760e37bcdba5ca7183",
      "min_rule_version": 2,
      "normalized_name": "fuel the flames",
      "oracle_hash": "cc94266044f2110700f72f897057280c",
      "required_effect_fields": {
        "battle_model_scope": "xmage_fixed_damage_all_matching_permanents_spell_v1"
      },
      "review_status": "verified"
    },
    {
      "card_name": "Hush",
      "execution_status": "auto",
      "forbid_annotation_only": true,
      "logical_rule_key": "battle_rule_v1:8cca937904da37d443131e25b0e866a5",
      "min_rule_version": 2,
      "normalized_name": "hush",
      "oracle_hash": "5c6bffbefc286bfe2ac0b15e7616894d",
      "required_effect_fields": {
        "battle_model_scope": "xmage_destroy_all_matching_permanents_spell_v1"
      },
      "review_status": "verified"
    },
    {
      "card_name": "Starstorm",
      "execution_status": "auto",
      "forbid_annotation_only": true,
      "logical_rule_key": "battle_rule_v1:529435595dfa892ca9d7d99e56608b91",
      "min_rule_version": 2,
      "normalized_name": "starstorm",
      "oracle_hash": "a9aa5a9ca98fa85f0d75ec12d20fc4b4",
      "required_effect_fields": {
        "battle_model_scope": "xmage_fixed_damage_all_matching_permanents_spell_v1"
      },
      "review_status": "verified"
    },
    {
      "card_name": "Sweltering Suns",
      "execution_status": "auto",
      "forbid_annotation_only": true,
      "logical_rule_key": "battle_rule_v1:d3f4bf0986864fe567d07cacb4c295a5",
      "min_rule_version": 2,
      "normalized_name": "sweltering suns",
      "oracle_hash": "060c6a7021fce3a0cafe3a08adfb38cb",
      "required_effect_fields": {
        "battle_model_scope": "xmage_fixed_damage_all_matching_permanents_spell_v1"
      },
      "review_status": "verified"
    }
  ],
  "status": "prepared_read_only_pending_apply_approval"
}
